supplychainpy/__init__.py
supplychainpy/launch_reports.py
supplychainpy/model_decision.py
supplychainpy/model_demand.py
supplychainpy/model_distribution.py
supplychainpy/model_inventory.py
supplychainpy/model_production.py
supplychainpy/model_warehouse.py
supplychainpy/simulate.py
supplychainpy/supplychain.py
supplychainpy/wsgi.py
supplychainpy/_csv_management/__init__.py
supplychainpy/_csv_management/_csv_manager.py
supplychainpy/_csv_management/_controller/__init__.py
supplychainpy/_csv_management/_controller/_update_db.py
supplychainpy/_csv_management/_model/__init__.py
supplychainpy/_csv_management/_model/_db_setup.py
supplychainpy/_helpers/__init__.py
supplychainpy/_helpers/_codes.py
supplychainpy/_helpers/_config_file_paths.py
supplychainpy/_helpers/_cpu_info.py
supplychainpy/_helpers/_data_cleansing.py
supplychainpy/_helpers/_db_connection.py
supplychainpy/_helpers/_decorators.py
supplychainpy/_helpers/_enum_formats.py
supplychainpy/_helpers/_mixins.py
supplychainpy/_helpers/_pickle_config.py
supplychainpy/_pickled/application_config.pickle
supplychainpy/_pickled/csv_management_config.pickle
supplychainpy/_pickled/dash.pickle
supplychainpy/bi/__init__.py
supplychainpy/bi/_analytical_heirachy_process.py
supplychainpy/bi/_recommendation_state_machine.py
supplychainpy/bi/_recommendations.py
supplychainpy/bi/recommendation_generator.py
supplychainpy/bot/__init__.py
supplychainpy/bot/_controller.py
supplychainpy/bot/_dash_engine.py
supplychainpy/bot/_dash_states.py
supplychainpy/bot/_helpers.py
supplychainpy/bot/dash.py
supplychainpy/demand/__init__.py
supplychainpy/demand/_evo_algo.cp35-win_amd64.pyd
supplychainpy/demand/_evolutionary_algorithms.py
supplychainpy/demand/_forecast_demand.py
supplychainpy/demand/_squared_error.cp35-win_amd64.pyd
supplychainpy/demand/regression.py
supplychainpy/distribution/__init__.py
supplychainpy/distribution/air_frieght_transport.py
supplychainpy-0.0.5.dist-info/DESCRIPTION.rst
supplychainpy-0.0.5.dist-info/METADATA
supplychainpy-0.0.5.dist-info/RECORD
supplychainpy-0.0.5.dist-info/WHEEL
supplychainpy-0.0.5.dist-info/entry_points.txt
supplychainpy-0.0.5.dist-info/metadata.json
supplychainpy-0.0.5.dist-info/top_level.txt
