Metadata-Version: 2.0
Name: supplychainpy
Version: 0.0.5
Summary: A library for supply chain, operations and manufacturing, analysis, modelling and simulation.
Home-page: https://github.com/KevinFasusi/supplychainpy
Author: Kevin Fasusi
Author-email: kevin@supplybi.com
License: BSD 3
Download-URL: https://github.com/KevinFasusi/supplychainpy/tarball/0.0.5
Keywords: supply chain,operations research,operations management,simulation
Platform: UNKNOWN
Classifier: Development Status :: 1 - Planning
Classifier: License :: OSI Approved :: BSD License
Classifier: Programming Language :: Python :: 3.5
Requires-Dist: Simplejson
Requires-Dist: cython
Requires-Dist: flask
Requires-Dist: flask-restful
Requires-Dist: flask-restless
Requires-Dist: flask-script
Requires-Dist: flask-sqlalchemy
Requires-Dist: flask-uploads
Requires-Dist: flask-wtf
Requires-Dist: numpy
Requires-Dist: pandas
Requires-Dist: scipy
Requires-Dist: sqlalchemy
Requires-Dist: textblob
Requires-Dist: wtforms
